rl_scan_artifactory/__init__.py
rl_scan_artifactory/app_base_with_logging.py
rl_scan_artifactory/artifactory_api.py
rl_scan_artifactory/artifactory_repo_info.py
rl_scan_artifactory/artifactory_repo_processor.py
rl_scan_artifactory/artifactory_to_portal_base.py
rl_scan_artifactory/constants.py
rl_scan_artifactory/docker_manifest_extract.py
rl_scan_artifactory/exceptions.py
rl_scan_artifactory/fileinfo.py
rl_scan_artifactory/generic_meta.py
rl_scan_artifactory/helpers.py
rl_scan_artifactory/main.py
rl_scan_artifactory/my_app.py
rl_scan_artifactory/my_args.py
rl_scan_artifactory/scan_cli_file.py
rl_scan_artifactory/spectra_assure_api.py
rl_scan_artifactory/version.py
rl_scan_artifactory/with_cleanup_porta.py
rl_scan_artifactory/artifactory_file_processor/__init__.py
rl_scan_artifactory/artifactory_file_processor/artifactory_file_processor_common.py
rl_scan_artifactory/artifactory_file_processor/artifactory_file_processor_default.py
rl_scan_artifactory/artifactory_file_processor/artifactory_file_processor_docker.py
rl_scan_artifactory/artifactory_file_processor/artifactory_file_processor_generic.py
rl_scan_artifactory/file_properties/__init__.py
rl_scan_artifactory/file_properties/file_properties_common.py
rl_scan_artifactory/file_properties/file_properties_default.py
rl_scan_artifactory/file_properties/file_properties_docker.py
rl_scan_artifactory/file_properties/file_properties_generic.py
rl_scan_artifactory/file_properties/file_properties_maven.py
rl_scan_artifactory/file_properties/file_properties_nuget.py
rl_scan_artifactory/file_properties/file_properties_rpm.py
rl_scan_artifactory/name_mangler/__init__.py
rl_scan_artifactory/name_mangler/name_mangler_common.py
rl_scan_artifactory/name_mangler/name_mangler_debian.py
rl_scan_artifactory/name_mangler/name_mangler_default.py
rl_scan_artifactory/name_mangler/name_mangler_docker.py
rl_scan_artifactory/name_mangler/name_mangler_gems.py
rl_scan_artifactory/name_mangler/name_mangler_generic.py
rl_scan_artifactory-1.0.4.dist-info/METADATA
rl_scan_artifactory-1.0.4.dist-info/WHEEL
rl_scan_artifactory-1.0.4.dist-info/entry_points.txt
rl_scan_artifactory-1.0.4.dist-info/licenses/LICENSE
rl_scan_artifactory-1.0.4.dist-info/RECORD
