Metadata-Version: 2.4
Name: rl-scan-artifactory
Version: 1.0.4
Summary: Python package to process files from Artifactory with Spectra Assure.
Project-URL: Bug Tracker, https://github.com/reversinglabs/rl-scan-artifactory/issues
Project-URL: Home Page, https://github.com/reversinglabs/rl-scan-artifactory
Project-URL: Repository, https://github.com/reversinglabs/rl-scan-artifactory
Author: ReversingLabs
Maintainer-email: ReversingLabs <support@reversinglabs.com>
License-Expression: MIT
License-File: LICENSE
Keywords: Python,Secure Software
Classifier: Environment :: Console
Classifier: Intended Audience :: Developers
Classifier: License :: OSI Approved :: MIT License
Classifier: Operating System :: OS Independent
Classifier: Programming Language :: Python :: 3.10
Classifier: Programming Language :: Python :: 3.11
Classifier: Programming Language :: Python :: 3.12
Classifier: Programming Language :: Python :: 3.13
Classifier: Topic :: Security
Classifier: Topic :: Software Development :: Libraries :: Python Modules
Requires-Python: >=3.10
Requires-Dist: python-dateutil
Requires-Dist: requests
Requires-Dist: spectra-assure-sdk>=1.0.4
